sleepness/__init__.py
sleepness/__main__.py
sleepness-0.5.dist-info/LICENSE
sleepness-0.5.dist-info/METADATA
sleepness-0.5.dist-info/WHEEL
sleepness-0.5.dist-info/entry_points.txt
sleepness-0.5.dist-info/top_level.txt
sleepness-0.5.dist-info/zip-safe
sleepness-0.5.dist-info/RECORD
